{"text":"\n      Controlling Praxisführung\n\n\n      Finanzielle Führung: Controlling Praxisführung zur Ertragsoptimierung\n\n\n      Zielgruppe\n\n\n      Praxisinhaber/-in und Praxismanager/-in (Voraussetzung ist der Einblick in die Finanzbuchhaltung)\n\n\n      Referentin\n\n\n      Barbara Themann\n\n\n      Lernziele\n\n\n      Als Zahnmediziner lernen Sie in der Universität keine Praxisführung. Holen Sie in kompakter Weise nach, was Sie über eine erfolgreiche, betriebswirtschaftliche Praxisführung wissen müssen. Wissen Sie, wann Sie gewinnerzielend oder nur kostendeckend arbeiten? Kennen Sie Ihren Behandler-Stundensatz, wissen Sie, ob dieser gewinnerzielend oder nur kostendeckend kalkuliert ist?\n\n\n      Ihr Vorteil: Die Teilnehmer erhalten sämtliche, im Seminar verwendeten, Excel-Tabellen mit Beispielkalkulationen und Formeln!\n\n\n      Seminarinhalte\n\n        * Definition Controlling\n        * Betriebswirtschaftliche Auswertung\n        * Praxisdaten für aussagekräftige Analysen\n        * Berechnung Behandler-, Assistenten- und DH-Stundensatz\n        * Kalkulationsbeispiele\n        * Kennzahlen für die Zahnarztpraxis\n        * Optimierung Beschaffungs- und Lagermanagement\n        * Instrumente zur Zielerreichung\n\n      Anerkennung\n\n\n      Nach erfolgreich absolviertem Seminar erhalten die Teilnehmenden ein Zertifikat inkl. Fortbildungspunkte: 1 Lektion entspricht einem 1 Fortbildungspunkt.\n\n\n    Kurs\n    Controlling Praxisführung\n\n\n    Ort\n    Baden\n\n\n    Preis *\n    CHF 750.00/Teilnehmer\n\n\n    * exkl. Lehrmittel und Prüfungsgebühr\n\n        Anmelden\n        Zurück zur Übersicht","markings":[{"startPosition":138,"length":97,"isWord":false,"types":["target_groups"],"provenanceInfo":null},{"startPosition":1233,"length":153,"isWord":false,"types":["certificates"],"provenanceInfo":null},{"startPosition":849,"length":356,"isWord":false,"types":["course_contents"],"provenanceInfo":null},{"startPosition":305,"length":509,"isWord":false,"types":["learning_objectives"],"provenanceInfo":null}],"documentURI":"i324492598007241219143785154809667386883.json"}